edx_i18n_tools-1.9.0.dist-info/licenses/LICENSE.txt
edx_i18n_tools-1.9.0.dist-info/licenses/NOTICE.txt
i18n/__init__.py
i18n/branch_cleanup.py
i18n/changed.py
i18n/config.py
i18n/converter.py
i18n/dummy.py
i18n/execute.py
i18n/extract.py
i18n/generate.py
i18n/main.py
i18n/segment.py
i18n/transifex.py
i18n/validate.py
edx_i18n_tools-1.9.0.dist-info/METADATA
edx_i18n_tools-1.9.0.dist-info/WHEEL
edx_i18n_tools-1.9.0.dist-info/entry_points.txt
edx_i18n_tools-1.9.0.dist-info/top_level.txt
edx_i18n_tools-1.9.0.dist-info/RECORD
