Metadata-Version: 2.4
Name: edx-i18n-tools
Version: 1.9.0
Summary: edX Internationalization Tools
Home-page: https://github.com/openedx/i18n-tools
Author: edX
Author-email: oscm@edx.org
License: Apache License 2.0
Classifier: Development Status :: 5 - Production/Stable
Classifier: Environment :: Web Environment
Classifier: Intended Audience :: Developers
Classifier: License :: OSI Approved :: Apache Software License
Classifier: Operating System :: OS Independent
Classifier: Programming Language :: Python
Classifier: Programming Language :: Python :: 3.11
Classifier: Programming Language :: Python :: 3.12
Classifier: Framework :: Django
Classifier: Framework :: Django :: 4.2
Classifier: Framework :: Django :: 5.2
License-File: LICENSE.txt
License-File: NOTICE.txt
Requires-Dist: Django
Requires-Dist: lxml[html_clean]
Requires-Dist: path<=16.16.0
Requires-Dist: polib
Requires-Dist: pyYaml
Dynamic: author
Dynamic: author-email
Dynamic: classifier
Dynamic: description
Dynamic: description-content-type
Dynamic: home-page
Dynamic: license
Dynamic: license-file
Dynamic: requires-dist
Dynamic: summary
